wig/__init__.py
wig/wig-ng.py
wig/consumers/__init__.py
wig/consumers/awdl.py
wig/consumers/base.py
wig/consumers/ccx.py
wig/consumers/hp.py
wig/consumers/p2p.py
wig/consumers/uncommon.py
wig/consumers/wps.py
wig/helpers/Processes.py
wig/helpers/__init__.py
wig/helpers/ccx.py
wig/helpers/ieee80211.py
wig/helpers/p2p.py
wig/helpers/radiotap.py
wig/helpers/wps.py
wig/helpers/network/__init__.py
wig/helpers/network/interfaces.py
wig/helpers/output/__init__.py
wig/helpers/output/writer.py
wig/producers/__init__.py
wig/producers/base.py
wig_ng-0.2.data/scripts/wig-ng.py
wig_ng-0.2.dist-info/LICENSE
wig_ng-0.2.dist-info/METADATA
wig_ng-0.2.dist-info/WHEEL
wig_ng-0.2.dist-info/top_level.txt
wig_ng-0.2.dist-info/RECORD
